Workbook

Sheet 1. Base de datos
A1: BASE DE DATOS — Sector Automotor y Mercado de Trabajo · Río Negro · III Trimestre 2022–2025
A2: Fuentes: DEyCRN · DNRPAyCP · INDEC · Sec. de Trabajo · Sec. de Energía de la Nación · Boletín Oficial Río Negro
A4: PATENTAMIENTOS · Río Negro (III Trimestre)
A5: Indicador | B5: 2022 | C5: 2023 | D5: 2024 | E5: 2025
A6: Automóviles patentados (unidades) | B6: 900 | C6: 1693 | D6: 1954 | E6: 2055
A7: Motovehículos patentados (unidades) | B7: 1300 | C7: 1385 | D7: 2200 | E7: 2887
A8: Total patentamientos (unidades) | B8: 2200 | C8: 3078 | D8: 4154 | E8: 4942
A9: Patentamientos Argentina – Total | C9: 238653 | D9: 270326 | E9: 332120
A10: Patentamientos Patagonia – Total | C10: 13732 | D10: 17738 | E10: 21410
A13: MERCADO LABORAL · Río Negro (III Trimestre)
A14: Indicador | B14: 2022 | C14: 2023 | D14: 2024 | E14: 2025
A15: Salario real ($ constantes 2004) | B15: 1234.4 | C15: 1128.9 | D15: 1171.2 | E15: 1428.1
A16: Índice salario real (base 2022=100) | B16: 100 | C16: 91.5 | D16: 94.9 | E16: 115.7
A17: Tasa desocupación (% PEA) | B17: 0.9 | C17: 1.1 | D17: 1.2 | E17: 1.2
A18: Tasa subocupación (% PEA) | B18: 2.5 | C18: 1.4 | D18: 2.3 | E18: 2
A19: Asalariados privados registrados (k) | B19: 106.3 | C19: 108.8 | D19: 108.9 | E19: 108.5
A20: Tasa de actividad (%) | B20: 42.2 | C20: 40.1 | D20: 40.4 | E20: 40.5
A23: ACTIVIDAD EMPRESARIAL Y COMBUSTIBLES
A24: Indicador | B24: 2022 | C24: 2023 | D24: 2024 | E24: 2025
A25: Nuevas sociedades comerciales (altas) | B25: 401 | C25: 533 | D25: 497 | E25: 550
A26: Precio Gas Oil G2 ($/litro) | B26: 141.49 | C26: 282.16 | D26: 1090.13 | E26: 1469
A27: Precio Nafta Súper ($/litro) | B27: 109.97 | C27: 221.69 | D27: 852.11 | E27: 1208.9
A28: Precio auto 0km estimado ($) | B28: 5000000 | C28: 8000000 | D28: 20000000 | E28: 28000000
A29: Precio moto 0km estimado ($) | B29: 500000 | C29: 1500000 | D29: 4000000 | E29: 6000000
A30: Salario mensual promedio jul-sep ($) | B30: 171508 | C30: 398189 | D30: 1299860 | E30: 1884754
A31: Puestos construcción (miles) | B31: 7.2 | C31: 6.8 | D31: 5.6 | E31: 5.2
A32: Puestos comercio+servicios (miles) | B32: 71.8 | C32: 74.6 | D32: 74.1 | E32: 75

Sheet 2. Indicadores
A1: INDICADORES CALCULADOS — Análisis cuantitativo del mercado automotor
A2: Todos los valores calculados con fórmulas desde Hoja 1. Las celdas azules son datos base; las negras son fórmulas.
A4: INDICADORES DE VARIACIÓN INTERANUAL
A5: Indicador | B5: Fuente | C5: 2022 | D5: 2023 | E5: 2024 | F5: 2025 | G5: Var. 22→23 | H5: Var. 23→24 | I5: Var. 24→25 | J5: Acum. 22→25
A6: Automóviles patentados | B6: Hoja 1 | C6: ='1. Base de datos'!B6 -> 900 | D6: ='1. Base de datos'!C6 -> 1693 | E6: ='1. Base de datos'!D6 -> 1954 | F6: ='1. Base de datos'!E6 -> 2055 | G6: =IFERROR((D6-C6)/C6,"N/D") -> 0.88111111 | H6: =IFERROR((E6-D6)/D6,"N/D") -> 0.15416421 | I6: =IFERROR((F6-E6)/E6,"N/D") -> 0.051688843 | J6: =IFERROR((F6-C6)/C6,"N/D") -> 1.2833333
A7: Motovehículos patentados | B7: Hoja 1 | C7: ='1. Base de datos'!B7 -> 1300 | D7: ='1. Base de datos'!C7 -> 1385 | E7: ='1. Base de datos'!D7 -> 2200 | F7: ='1. Base de datos'!E7 -> 2887 | G7: =IFERROR((D7-C7)/C7,"N/D") -> 0.065384615 | H7: =IFERROR((E7-D7)/D7,"N/D") -> 0.58844765 | I7: =IFERROR((F7-E7)/E7,"N/D") -> 0.31227273 | J7: =IFERROR((F7-C7)/C7,"N/D") -> 1.2207692
A8: Total patentamientos | B8: Hoja 1 | C8: ='1. Base de datos'!B8 -> 2200 | D8: ='1. Base de datos'!C8 -> 3078 | E8: ='1. Base de datos'!D8 -> 4154 | F8: ='1. Base de datos'!E8 -> 4942 | G8: =IFERROR((D8-C8)/C8,"N/D") -> 0.39909091 | H8: =IFERROR((E8-D8)/D8,"N/D") -> 0.34957765 | I8: =IFERROR((F8-E8)/E8,"N/D") -> 0.18969668 | J8: =IFERROR((F8-C8)/C8,"N/D") -> 1.2463636
A9: Salario real (ctes. 2004) | B9: Hoja 1 | C9: ='1. Base de datos'!B15 -> 1234.4 | D9: ='1. Base de datos'!C15 -> 1128.9 | E9: ='1. Base de datos'!D15 -> 1171.2 | F9: ='1. Base de datos'!E15 -> 1428.1 | G9: =IFERROR((D9-C9)/C9,"N/D") -> -0.085466623 | H9: =IFERROR((E9-D9)/D9,"N/D") -> 0.037470104 | I9: =IFERROR((F9-E9)/E9,"N/D") -> 0.21934768 | J9: =IFERROR((F9-C9)/C9,"N/D") -> 0.15691834
A10: Índice salarial (2022=100) | B10: Hoja 1 | C10: ='1. Base de datos'!B16 -> 100 | D10: ='1. Base de datos'!C16 -> 91.5 | E10: ='1. Base de datos'!D16 -> 94.9 | F10: ='1. Base de datos'!E16 -> 115.7 | G10: =IFERROR((D10-C10)/C10,"N/D") -> -0.085 | H10: =IFERROR((E10-D10)/D10,"N/D") -> 0.03715847 | I10: =IFERROR((F10-E10)/E10,"N/D") -> 0.21917808 | J10: =IFERROR((F10-C10)/C10,"N/D") -> 0.157
A11: Desocupación (%) | B11: Hoja 1 | C11: ='1. Base de datos'!B17 -> 0.9 | D11: ='1. Base de datos'!C17 -> 1.1 | E11: ='1. Base de datos'!D17 -> 1.2 | F11: ='1. Base de datos'!E17 -> 1.2 | G11: =D11-C11 -> 0.2 | H11: =E11-D11 -> 0.1 | I11: =F11-E11 -> 0 | J11: =F11-C11 -> 0.3
A12: Subocupación (%) | B12: Hoja 1 | C12: ='1. Base de datos'!B18 -> 2.5 | D12: ='1. Base de datos'!C18 -> 1.4 | E12: ='1. Base de datos'!D18 -> 2.3 | F12: ='1. Base de datos'!E18 -> 2 | G12: =D12-C12 -> -1.1 | H12: =E12-D12 -> 0.9 | I12: =F12-E12 -> -0.3 | J12: =F12-C12 -> -0.5
A13: Asalariados privados (k) | B13: Hoja 1 | C13: ='1. Base de datos'!B19 -> 106.3 | D13: ='1. Base de datos'!C19 -> 108.8 | E13: ='1. Base de datos'!D19 -> 108.9 | F13: ='1. Base de datos'!E19 -> 108.5 | G13: =IFERROR((D13-C13)/C13,"N/D") -> 0.023518344 | H13: =IFERROR((E13-D13)/D13,"N/D") -> 0.00091911765 | I13: =IFERROR((F13-E13)/E13,"N/D") -> -0.0036730946 | J13: =IFERROR((F13-C13)/C13,"N/D") -> 0.020696143
A14: Nuevas empresas (altas) | B14: Hoja 1 | C14: ='1. Base de datos'!B25 -> 401 | D14: ='1. Base de datos'!C25 -> 533 | E14: ='1. Base de datos'!D25 -> 497 | F14: ='1. Base de datos'!E25 -> 550 | G14: =IFERROR((D14-C14)/C14,"N/D") -> 0.32917706 | H14: =IFERROR((E14-D14)/D14,"N/D") -> -0.067542214 | I14: =IFERROR((F14-E14)/E14,"N/D") -> 0.10663984 | J14: =IFERROR((F14-C14)/C14,"N/D") -> 0.37157107
A15: Precio Gas Oil G2 ($/L) | B15: Hoja 1 | C15: ='1. Base de datos'!B26 -> 141.49 | D15: ='1. Base de datos'!C26 -> 282.16 | E15: ='1. Base de datos'!D26 -> 1090.13 | F15: ='1. Base de datos'!E26 -> 1469 | G15: =IFERROR((D15-C15)/C15,"N/D") -> 0.99420454 | H15: =IFERROR((E15-D15)/D15,"N/D") -> 2.8635172 | I15: =IFERROR((F15-E15)/E15,"N/D") -> 0.34754571 | J15: =IFERROR((F15-C15)/C15,"N/D") -> 9.3823592
A18: INDICADORES DERIVADOS Y RATIOS
A19: Indicador derivado | B19: Fórmula | C19: 2022 | D19: 2023 | E19: 2024 | F19: 2025 | G19: Var. 22→23 | H19: Var. 23→24 | I19: Var. 24→25 | J19: Tendencia
A20: Ratio motos / autos | B20: motos ÷ autos | C20: =C7/C6 -> 1.4444444 | D20: =D7/D6 -> 0.81807442 | E20: =E7/E6 -> 1.1258956 | F20: =F7/F6 -> 1.4048662 | G20: =IFERROR((D20-C20)/C20,"N/D") -> -0.43364078 | H20: =IFERROR((E20-D20)/D20,"N/D") -> 0.37627527 | I20: =IFERROR((F20-E20)/E20,"N/D") -> 0.2477766 | J20: ↑ motos ganan terreno
A21: Participación motos en total (%) | B21: motos ÷ total | C21: =C7/C8 -> 0.59090909 | D21: =D7/D8 -> 0.44996751 | E21: =E7/E8 -> 0.52961001 | F21: =F7/F8 -> 0.58417645 | G21: =IFERROR((D21-C21)/C21,"N/D") -> -0.23851652 | H21: =IFERROR((E21-D21)/D21,"N/D") -> 0.17699612 | I21: =IFERROR((F21-E21)/E21,"N/D") -> 0.10303135 | J21: ↑ motos suman participación
A22: Participación autos en total (%) | B22: autos ÷ total | C22: =C6/C8 -> 0.40909091 | D22: =D6/D8 -> 0.55003249 | E22: =E6/E8 -> 0.47038999 | F22: =F6/F8 -> 0.41582355 | G22: =IFERROR((D22-C22)/C22,"N/D") -> 0.34452386 | H22: =IFERROR((E22-D22)/D22,"N/D") -> -0.144796 | I22: =IFERROR((F22-E22)/E22,"N/D") -> -0.11600254 | J22: ↓ autos pierden participación
A23: Salarios equiv. para auto 0km | B23: P.auto ÷ sal.mensual | C23: ='1. Base de datos'!B28/'1. Base de datos'!B30 -> 29.153159 | D23: ='1. Base de datos'!C28/'1. Base de datos'!C30 -> 20.090962 | E23: ='1. Base de datos'!D28/'1. Base de datos'!D30 -> 15.386272 | F23: ='1. Base de datos'!E28/'1. Base de datos'!E30 -> 14.85605 | G23: =IFERROR((D23-C23)/C23,"N/D") -> -0.31084786 | H23: =IFERROR((E23-D23)/D23,"N/D") -> -0.23416945 | I23: =IFERROR((F23-E23)/E23,"N/D") -> -0.034460731 | J23: ↓ auto más inalcanzable
A24: Salarios equiv. para moto 0km | B24: P.moto ÷ sal.mensual | C24: ='1. Base de datos'!B29/'1. Base de datos'!B30 -> 2.9153159 | D24: ='1. Base de datos'!C29/'1. Base de datos'!C30 -> 3.7670553 | E24: ='1. Base de datos'!D29/'1. Base de datos'!D30 -> 3.0772545 | F24: ='1. Base de datos'!E29/'1. Base de datos'!E30 -> 3.1834393 | G24: =IFERROR((D24-C24)/C24,"N/D") -> 0.29216026 | H24: =IFERROR((E24-D24)/D24,"N/D") -> -0.18311408 | I24: =IFERROR((F24-E24)/E24,"N/D") -> 0.03450636 | J24: ≈ moto se mantiene accesible
A25: Cuota auto 60c (% del salario) | B25: P.auto ÷ 60 ÷ sal | C25: ='1. Base de datos'!B28/60/'1. Base de datos'!B30 -> 0.48588598 | D25: ='1. Base de datos'!C28/60/'1. Base de datos'!C30 -> 0.33484936 | E25: ='1. Base de datos'!D28/60/'1. Base de datos'!D30 -> 0.25643787 | F25: ='1. Base de datos'!E28/60/'1. Base de datos'!E30 -> 0.24760084 | G25: =IFERROR((D25-C25)/C25,"N/D") -> -0.31084786 | H25: =IFERROR((E25-D25)/D25,"N/D") -> -0.23416945 | I25: =IFERROR((F25-E25)/E25,"N/D") -> -0.034460731 | J25: ≈ cuota alta pero estable
A26: Cuota moto 24c (% del salario) | B26: P.moto ÷ 24 ÷ sal | C26: ='1. Base de datos'!B29/24/'1. Base de datos'!B30 -> 0.1214715 | D26: ='1. Base de datos'!C29/24/'1. Base de datos'!C30 -> 0.15696064 | E26: ='1. Base de datos'!D29/24/'1. Base de datos'!D30 -> 0.12821894 | F26: ='1. Base de datos'!E29/24/'1. Base de datos'!E30 -> 0.13264331 | G26: =IFERROR((D26-C26)/C26,"N/D") -> 0.29216026 | H26: =IFERROR((E26-D26)/D26,"N/D") -> -0.18311408 | I26: =IFERROR((F26-E26)/E26,"N/D") -> 0.03450636 | J26: ✓ moto sigue accesible

Sheet 3. Dashboard
A1: DASHBOARD EJECUTIVO — Mercado Automotor Río Negro 2022–2025
A2: III Trimestre de cada año | Fuente: DEyCRN · DNRPAyCP · INDEC · Sec. de Energía
A4: 🚗 AUTOS 2025 | C4: 🛵 MOTOS 2025 | E4: 📈 SAL. REAL IDX | G4: 🏢 NUEVAS EMP. | I4: ⛽ COMBUSTIBLE | K4: 💰 SAL. MENSUAL
A5: ='2. Indicadores'!F6 -> 2055 | C5: ='2. Indicadores'!F7 -> 2887 | E5: ='2. Indicadores'!F10 -> 115.7 | G5: ='2. Indicadores'!F14 -> 550 | I5: ='2. Indicadores'!F15 -> 1469 | K5: ='1. Base de datos'!E30 -> 1884754
A6: units | C6: units | E6: 2022=100 | G6: altas 2025 | I6: $/litro GO2 | K6: jul-sep 2025
A7: =IFERROR(('2. Indicadores'!F6-'2. Indicadores'!C6)/'2. Indicadores'!C6,"") -> 1.2833333 | C7: =IFERROR(('2. Indicadores'!F7-'2. Indicadores'!C7)/'2. Indicadores'!C7,"") -> 1.2207692 | E7: =IFERROR(('2. Indicadores'!F10-'2. Indicadores'!C10)/'2. Indicadores'!C10,"") -> 0.157 | G7: =IFERROR(('2. Indicadores'!F14-'2. Indicadores'!C14)/'2. Indicadores'!C14,"") -> 0.37157107 | I7: =IFERROR(('2. Indicadores'!F15-'2. Indicadores'!C15)/'2. Indicadores'!C15,"") -> 9.3823592 | K7: =IFERROR(('1. Base de datos'!E30-'1. Base de datos'!B30)/'1. Base de datos'!B30,"") -> 9.9893066
A9: COMPARATIVA 2022 vs 2025 | H9: ACCESIBILIDAD 2025 — ¿Cuánto necesitás ganar para comprarlo?
A10: Indicador | B10: 2022 | C10: 2025 | D10: Var. Absoluta | E10: Var. % | F10: Señal | H10: Vehículo | I10: Precio ($) | J10: Sal.mensual ($) | K10: Salarios equiv. | L10: Plazo | M10: Cuota ($) | N10: Cuota / Sal. | O10: Nivel
A11: Automóviles | B11: ='2. Indicadores'!C6 -> 900 | C11: ='2. Indicadores'!F6 -> 2055 | D11: =C11-B11 -> 1155 | E11: =IFERROR((C11-B11)/B11,"N/D") -> 1.2833333 | F11: 🟢 +128% récord | H11: 🚗 Auto 0km | I11: ='1. Base de datos'!E28 -> 28000000 | J11: ='1. Base de datos'!E30 -> 1884754 | K11: =I11/J11 -> 14.85605 | L11: 60 | M11: =I11/L11 -> 466666.67 | N11: =M11/J11 -> 0.24760084 | O11: ⚠ Alta cuota
A12: Motovehículos | B12: ='2. Indicadores'!C7 -> 1300 | C12: ='2. Indicadores'!F7 -> 2887 | D12: =C12-B12 -> 1587 | E12: =IFERROR((C12-B12)/B12,"N/D") -> 1.2207692 | F12: 🟢 +122% récord | H12: 🚗 Auto usado | I12: ='1. Base de datos'!E29 -> 6000000 | J12: ='1. Base de datos'!E30 -> 1884754 | K12: =I12/J12 -> 3.1834393 | L12: 36 | M12: =I12/L12 -> 166666.67 | N12: =M12/J12 -> 0.08842887 | O12: ✓ Accesible
A13: Total patentam. | B13: ='2. Indicadores'!C8 -> 2200 | C13: ='2. Indicadores'!F8 -> 4942 | D13: =C13-B13 -> 2742 | E13: =IFERROR((C13-B13)/B13,"N/D") -> 1.2463636 | F13: 🟢 +185% total | H13: 🛵 Moto 0km | I13: ='1. Base de datos'!E31 -> 5.2 | J13: ='1. Base de datos'!E30 -> 1884754 | K13: =I13/J13 -> 2.7589807e-06 | L13: 24 | M13: =I13/L13 -> 0.21666667 | N13: =M13/J13 -> 1.1495753e-07 | O13: ✓ Muy accesible
A14: Salario real idx | B14: ='2. Indicadores'!C10 -> 100 | C14: ='2. Indicadores'!F10 -> 115.7 | D14: =C14-B14 -> 15.7 | E14: =IFERROR((C14-B14)/B14,"N/D") -> 0.157 | F14: 🟢 +15,7% recupera | H14: 🛵 Moto usada | I14: ='1. Base de datos'!E32 -> 75 | J14: ='1. Base de datos'!E30 -> 1884754 | K14: =I14/J14 -> 3.9792992e-05 | L14: 12 | M14: =I14/L14 -> 6.25 | N14: =M14/J14 -> 3.3160826e-06 | O14: ✓ Capital inmediato
A15: Nuevas empresas | B15: ='2. Indicadores'!C14 -> 401 | C15: ='2. Indicadores'!F14 -> 550 | D15: =C15-B15 -> 149 | E15: =IFERROR((C15-B15)/B15,"N/D") -> 0.37157107 | F15: 🟢 +37% activo
A16: Combustible $/L | B16: ='2. Indicadores'!C15 -> 141.49 | C16: ='2. Indicadores'!F15 -> 1469 | D16: =C16-B16 -> 1327.51 | E16: =IFERROR((C16-B16)/B16,"N/D") -> 9.3823592 | F16: 🔴 +938% crisis
A18: EVOLUCIÓN TRIMESTRAL — Todos los indicadores clave
A19: Indicador | B19: 2022 | C19: 2023 | D19: 2024 | E19: 2025 | F19: 22→23 | G19: 23→24 | H19: 24→25 | I19: Mejor año | J19: Interpretación
A20: Automóviles | B20: ='2. Indicadores'!C6 -> 900 | C20: ='2. Indicadores'!D6 -> 1693 | D20: ='2. Indicadores'!E6 -> 1954 | E20: ='2. Indicadores'!F6 -> 2055 | F20: =IFERROR((C20-B20)/B20,"") -> 0.88111111 | G20: =IFERROR((D20-C20)/C20,"") -> 0.15416421 | H20: =IFERROR((E20-D20)/D20,"") -> 0.051688843 | I20: 2025 | J20: Crecimiento sostenido. Moderación en 2025.
A21: Motovehículos | B21: ='2. Indicadores'!C7 -> 1300 | C21: ='2. Indicadores'!D7 -> 1385 | D21: ='2. Indicadores'!E7 -> 2200 | E21: ='2. Indicadores'!F7 -> 2887 | F21: =IFERROR((C21-B21)/B21,"") -> 0.065384615 | G21: =IFERROR((D21-C21)/C21,"") -> 0.58844765 | H21: =IFERROR((E21-D21)/D21,"") -> 0.31227273 | I21: 2025 | J21: Explosión 2024 (+58%). Motor del mercado.
A22: Salario real idx | B22: ='2. Indicadores'!C10 -> 100 | C22: ='2. Indicadores'!D10 -> 91.5 | D22: ='2. Indicadores'!E10 -> 94.9 | E22: ='2. Indicadores'!F10 -> 115.7 | F22: =IFERROR((C22-B22)/B22,"") -> -0.085 | G22: =IFERROR((D22-C22)/C22,"") -> 0.03715847 | H22: =IFERROR((E22-D22)/D22,"") -> 0.21917808 | I22: 2025 | J22: Mínimo en 2023. Fuerte recuperación 2025.
A23: Desocupación % | B23: ='2. Indicadores'!C11 -> 0.9 | C23: ='2. Indicadores'!D11 -> 1.1 | D23: ='2. Indicadores'!E11 -> 1.2 | E23: ='2. Indicadores'!F11 -> 1.2 | F23: =IFERROR((C23-B23)/B23,"") -> 0.22222222 | G23: =IFERROR((D23-C23)/C23,"") -> 0.090909091 | H23: =IFERROR((E23-D23)/D23,"") -> 0 | I23: 2022 | J23: Siempre muy baja. Mercado laboral pleno.
A24: Nuevas empresas | B24: ='2. Indicadores'!C14 -> 401 | C24: ='2. Indicadores'!D14 -> 533 | D24: ='2. Indicadores'!E14 -> 497 | E24: ='2. Indicadores'!F14 -> 550 | F24: =IFERROR((C24-B24)/B24,"") -> 0.32917706 | G24: =IFERROR((D24-C24)/C24,"") -> -0.067542214 | H24: =IFERROR((E24-D24)/D24,"") -> 0.10663984 | I24: 2025 | J24: Pico 2023. Tendencia alcista sostenida.
A25: Combustible $/L | B25: ='2. Indicadores'!C15 -> 141.49 | C25: ='2. Indicadores'!D15 -> 282.16 | D25: ='2. Indicadores'!E15 -> 1090.13 | E25: ='2. Indicadores'!F15 -> 1469 | F25: =IFERROR((C25-B25)/B25,"") -> 0.99420454 | G25: =IFERROR((D25-C25)/C25,"") -> 2.8635172 | H25: =IFERROR((E25-D25)/D25,"") -> 0.34754571 | I25: 2022 | J25: ×10 en 4 años. Mayor subida en 2024.
A28: DATOS PARA GRÁFICOS (índices base 2022=100)
A29: Serie | B29: 2022 | C29: 2023 | D29: 2024 | E29: 2025
A30: Autos (idx) | B30: ='2. Indicadores'!C6/'2. Indicadores'!C6*100 -> 100 | C30: ='2. Indicadores'!D6/'2. Indicadores'!C6*100 -> 188.11111 | D30: ='2. Indicadores'!E6/'2. Indicadores'!C6*100 -> 217.11111 | E30: ='2. Indicadores'!F6/'2. Indicadores'!C6*100 -> 228.33333
A31: Motos (idx) | B31: ='2. Indicadores'!C7/'2. Indicadores'!C7*100 -> 100 | C31: ='2. Indicadores'!D7/'2. Indicadores'!C7*100 -> 106.53846 | D31: ='2. Indicadores'!E7/'2. Indicadores'!C7*100 -> 169.23077 | E31: ='2. Indicadores'!F7/'2. Indicadores'!C7*100 -> 222.07692
A32: Sal.real (idx) | B32: ='2. Indicadores'!C10/'2. Indicadores'!C10*100 -> 100 | C32: ='2. Indicadores'!D10/'2. Indicadores'!C10*100 -> 91.5 | D32: ='2. Indicadores'!E10/'2. Indicadores'!C10*100 -> 94.9 | E32: ='2. Indicadores'!F10/'2. Indicadores'!C10*100 -> 115.7

Sheet 4. Conclusiones
A1: CONCLUSIONES ANALÍTICAS — Mercado Automotor Río Negro 2022–2025
A2: Respuestas basadas en datos · III Trimestre de cada año · Fuente: DEyCRN · DNRPAyCP · INDEC
A4: 1. EFECTO SUSTITUCIÓN AUTOS → MOTOS
A5: Pregunta: ¿Existe sustitución cuando cae el salario?
A6: • CONFIRMADA PARCIALMENTE. Cuando el salario real cayó -8,5% en 2023, las motos crecieron +28,2% mientras los autos crecían más lento.
A7: • El ratio motos/autos pasó de 1,44x (2022) a 1,13x (2024) y se mantiene en 1,40x (2025), siempre por encima de 1.
A8: • La sustitución no es total: la moto no reemplaza al auto como bien de confort, sino que actúa como alternativa productiva cuando el ingreso no alcanza para el crédito automotor.
A9: • IMPLICANCIA: En momentos de restricción salarial, el mercado de motos se convierte en el termómetro más sensible de la economía popular.
A10: ► CONCLUSIÓN: Sí existe sustitución, pero es sustitución funcional (herramienta de trabajo) más que de estilo de vida.
A12: 2. MOTOS Y TRABAJO INDEPENDIENTE
A13: Pregunta: ¿El crecimiento de motos está asociado al autoempleo?
A14: • CONFIRMADO, PERO NO POR SUBOCUPACIÓN. La correlación motos–subocupación es casi nula (r≈0,08).
... A53: TABLA RESUMEN — PREGUNTAS Y RESPUESTAS EN UNA LÍNEA
A54: N° | B54: Pregunta | D54: Evidencia clave | E54: Señal negocio
A55: 1 | B55: ¿Existe sustitución autos→motos? | D55: Sí, cuando cae el salario | E55: Motos +28% con sal. -8,5% en 2023 | F55: Stock motos cuando salario baja
A56: 2 | B56: ¿Motos = trabajo independiente? | D56: Sí, son capital productivo | E56: Correl. con empresas (r=0,61) | F56: Target: emprendedores y delivery
A57: 3 | B57: ¿Combustible y actividad? | D57: Combustible reshape sectores | E57: Construcción -28% vs Servicios +4% | F57: Motos eficientes ganan mercado
A58: 4 | B58: ¿Qué vehículo es más sensible? | D58: Autos al alza / Motos siempre | E58: Elasticidad autos >4 vs motos <2 | F58: Autos: lanzar con salario en alza
A59: 5 | B59: ¿Crecimiento o adaptación? | D59: Las dos: +125% total del mercado | E59: Motos suben el mix en crisis | F59: Mix cambia con el ciclo económico
A60: 6 | B60: ¿El auto dejó de ser objetivo? | D60: No, pero necesita crédito | E60: 15 salarios equiv. en 2025 | F60: Auto usado = mayor oportunidad
